.gitignore
MANIFEST.in
README.rst
bitbucket-pipelines.yml
requirements.txt
setup.py
pamel.egg-info/PKG-INFO
pamel.egg-info/SOURCES.txt
pamel.egg-info/dependency_links.txt
pamel.egg-info/requires.txt
pamel.egg-info/top_level.txt
pamel.egg-info/zip-safe
paml/__init__.py
paml/automl.py
paml/metrics/Metrics.py
paml/metrics/__init__.py
paml/searches/Base.py
paml/searches/GridSearch.py
paml/searches/GridSearchCV.py
paml/searches/OptunaSearch.py
paml/searches/SearchSpaces.py
paml/searches/__init__.py
paml/searches/optuna_objectives.py
paml/searches/wrapper_catboost.py