Metadata-Version: 2.1
Name: pamel
Version: 0.0.70
Summary: UNKNOWN
Home-page: UNKNOWN
Author: Rute Souza de Abreu
Author-email: rute.s.abreu@gmail.com
License: MIT
Keywords: automl,credit
Platform: UNKNOWN
Classifier: Development Status :: 2 - Pre-Alpha
Classifier: License :: OSI Approved :: MIT License
Classifier: Programming Language :: Python :: 3.8
Classifier: Topic :: Scientific/Engineering :: Artificial Intelligence
